AUTHORS
LICENSE
MANIFEST.in
Makefile
README.rst
bootstrap.py
buildout.cfg
setup.cfg
setup.py
pkg/python-project.mk
pkg/rhel/python-cycle.spec
src/cycle/__init__.py
src/cycle/baseshell.py
src/cycle/meta.py
src/cycle/shell.py
src/cycle/utils.py
src/cycle.egg-info/PKG-INFO
src/cycle.egg-info/SOURCES.txt
src/cycle.egg-info/dependency_links.txt
src/cycle.egg-info/entry_points.txt
src/cycle.egg-info/not-zip-safe
src/cycle.egg-info/requires.txt
src/cycle.egg-info/top_level.txt
src/cycle/commands/__init__.py
src/cycle/commands/prototype.py
src/cycle/data/prototypes/cycle.prototypes.python.base/.gitignore
src/cycle/data/prototypes/cycle.prototypes.python.base/AUTHORS.tmpl
src/cycle/data/prototypes/cycle.prototypes.python.base/README.rst.tmpl
src/cycle/data/prototypes/cycle.prototypes.python.base/setup.cfg
src/cycle/data/prototypes/cycle.prototypes.python.base/setup.py.tmpl
src/cycle/data/prototypes/cycle.prototypes.python.base/wizard.json
src/cycle/data/prototypes/cycle.prototypes.python.base/src/++project_name++/__init__.py
src/cycle/data/prototypes/cycle.prototypes.python.base/src/++project_name++/meta.py.tmpl
src/cycle/generators/__init__.py
src/cycle/generators/generic.py