Metadata-Version: 1.1
Name: cycle
Version: 0.1.0
Summary: A Python software build management tool inspired by Maven
Home-page: https://github.com/refnode/cycle
Author: refnode
Author-email: refnode@gmail.com
License: Apache License, Version 2.0
Keywords: cycle code generator builder maven
Platform: UNKNOWN
Classifier: Development Status :: 2 - Pre-Alpha    
Classifier: Environment :: Console
Classifier: Intended Audience :: Developers
Classifier: Intended Audience :: Information Technology
Classifier: Intended Audience :: System Administrators
Classifier: License :: OSI Approved :: Apache Software License
Classifier: Operating System :: POSIX :: Linux
Classifier: Programming Language :: Python
Classifier: Programming Language :: Python :: 2.7
Classifier: Topic :: Software Development :: Code Generators
Classifier: Topic :: Software Development :: Libraries :: Python Modules
Classifier: Topic :: Utilities
